LICENSE
bytechomp/__init__.py
bytechomp/basic_parsing_element.py
bytechomp/byte_order.py
bytechomp/data_descriptor.py
bytechomp/datatypes/__init__.py
bytechomp/datatypes/declarations.py
bytechomp/datatypes/lookups.py
bytechomp/py.typed
bytechomp/reader.py
bytechomp/serialization.py
bytechomp-0.3.0.dist-info/LICENSE
bytechomp-0.3.0.dist-info/WHEEL
bytechomp-0.3.0.dist-info/METADATA
bytechomp-0.3.0.dist-info/RECORD
