Metadata-Version: 2.1
Name: bytechomp
Version: 0.3.0
Summary: A pure python, declarative binary protocol parser & generator using dataclasses and type hinting.
Home-page: https://github.com/AndrewSpittlemeister/bytechomp
License: MIT
Author: Andrew Spittlemeister
Author-email: andrew.spittlemeister@pm.me
Requires-Python: >=3.10,<3.11
Classifier: License :: OSI Approved :: MIT License
Classifier: Programming Language :: Python :: 3
Classifier: Programming Language :: Python :: 3.10
Project-URL: Repository, https://github.com/AndrewSpittlemeister/bytechomp
